{
  "type": "Collection",
  "id": "example_collection",
  "stac_version": "1.1.0",
  "description": "collection/exp_desc",
  "links": [
    {
      "rel": "root",
      "href": "../../catalog.json",
      "type": "application/json",
      "title": "Template Catalog"
    },
    {
      "rel": "item",
      "href": "./nlcd-annual-conus/2021/nlcd_2021_cog_v2.json",
      "type": "application/geo+json",
      "datetime": "2021-01-01T00:00:00Z"
    },
    {
      "rel": "item",
      "href": "./nlcd-annual-conus/2019/nlcd_2019_cog_v2.json",
      "type": "application/geo+json",
      "datetime": "2019-01-01T00:00:00Z"
    },
    {
      "rel": "item",
      "href": "./nlcd-annual-conus/2016/nlcd_2016_cog_v2.json",
      "type": "application/geo+json",
      "datetime": "2016-01-01T00:00:00Z"
    },
    {
      "rel": "item",
      "href": "./nlcd-annual-conus/2013/nlcd_2013_cog_v2.json",
      "type": "application/geo+json",
      "datetime": "2013-01-01T00:00:00Z"
    },
    {
      "rel": "item",
      "href": "./nlcd-annual-conus/2011/nlcd_2011_cog_v2.json",
      "type": "application/geo+json",
      "datetime": "2011-01-01T00:00:00Z"
    },
    {
      "rel": "item",
      "href": "./nlcd-annual-conus/2008/nlcd_2008_cog_v2.json",
      "type": "application/geo+json",
      "datetime": "2008-01-01T00:00:00Z"
    },
    {
      "rel": "item",
      "href": "./nlcd-annual-conus/2006/nlcd_2006_cog_v2.json",
      "type": "application/geo+json",
      "datetime": "2006-01-01T00:00:00Z"
    },
    {
      "rel": "item",
      "href": "./nlcd-annual-conus/2004/nlcd_2004_cog_v2.json",
      "type": "application/geo+json",
      "datetime": "2004-01-01T00:00:00Z"
    },
    {
      "rel": "item",
      "href": "./nlcd-annual-conus/2001/nlcd_2001_cog_v2.json",
      "type": "application/geo+json",
      "datetime": "2001-01-01T00:00:00Z"
    },
    {
      "rel": "xyz",
      "href": "https://openveda.cloud/api/raster/cog/tiles/WebMercatorQuad/{z}/{x}/{y}?resampling_method=nearest&bidx=1",
      "type": "image/png",
      "title": "example_collection"
    },
    {
      "rel": "parent",
      "href": "../collection.json",
      "type": "application/json",
      "title": "Example collection"
    }
  ],
  "themes": [
    "features",
    "monthly-diff"
  ],
  "tags": [
    "vector",
    "feature",
    "no2"
  ],
  "agency": [
    "Example agency"
  ],
  "subcode": "EX2",
  "sensor": [
    "Sensorname"
  ],
  "satellite": [
    "Satellitename"
  ],
  "insituSources": [
    "Other insitu data"
  ],
  "endpointtype": "VEDA_cog",
  "title": "Example collection",
  "extent": {
    "spatial": {
      "bbox": [
        [
          -130.23282801589895,
          21.742307778016638,
          -63.672191850655295,
          49.177063191389536
        ]
      ]
    },
    "temporal": {
      "interval": [
        [
          "2001-01-01T00:00:00Z",
          "2021-01-01T00:00:00Z"
        ]
      ]
    }
  },
  "license": "other"
}